django_google_oauth_rest/__init__.py
django_google_oauth_rest/admin.py
django_google_oauth_rest/apps.py
django_google_oauth_rest/generate_url.py
django_google_oauth_rest/tests.py
django_google_oauth_rest/views.py
django_google_oauth_rest-1.0.dist-info/LICENSE
django_google_oauth_rest-1.0.dist-info/METADATA
django_google_oauth_rest-1.0.dist-info/WHEEL
django_google_oauth_rest-1.0.dist-info/top_level.txt
django_google_oauth_rest-1.0.dist-info/RECORD
