Metadata-Version: 2.1
Name: django-google-oauth-rest
Version: 1.0
Summary: "Django Google auth"
Home-page: https://github.com/ahmad-00/django_google_oauth_rest
Author: Ahmad Mohammadi
Author-email: mohammadi.ahmad00@gmail.com
License: MIT
Keywords: django google auth oauth
Platform: UNKNOWN
Classifier: Environment :: Web Environment
Classifier: Framework :: Django
Classifier: Intended Audience :: Developers
Classifier: License :: OSI Approved :: MIT License
Classifier: Operating System :: OS Independent
Classifier: Programming Language :: Python :: 3
Classifier: Topic :: Software Development :: Libraries :: Python Modules
Requires-Python: >=3
